{
  "tables": [
    {
      "table_title": "Performance Comparison on COCO Dataset",
      "is_baseline": false,
      "group_ns": null,
      "headers": [
        "Model",
        "mAP (%)",
        "Inference Time (ms)"
      ],
      "data": [
        [
          "YOLOv3",
          "37.1",
          "50"
        ],
        [
          "YOLOv4",
          "40.5",
          "55"
        ],
        [
          "L-ROD",
          "43.2",
          "35"
        ]
      ],
      "table_note": "Performance comparison of different models on the COCO dataset, showing mean average precision (mAP) and inference time."
    }
  ]
}