{
  "tables": [
    {
      "table_title": "Comparison of Diagnostic Accuracy Between Human-AI Collaborative System and Standalone AI Systems",
      "is_baseline": false,
      "group_ns": null,
      "headers": [
        "System",
        "Accuracy",
        "Sensitivity",
        "Specificity"
      ],
      "data": [
        [
          "Human-AI Collaborative System",
          "92%",
          "91%",
          "93%"
        ],
        [
          "Standalone AI System",
          "85%",
          "83%",
          "86%"
        ]
      ],
      "table_note": null
    }
  ]
}