{
  "tables": [
    {
      "table_title": "Accuracy comparison between our framework and state-of-the-art methods on the AEMO dataset.",
      "is_baseline": false,
      "group_ns": null,
      "headers": [
        "Method",
        "Accuracy"
      ],
      "data": [
        [
          "Our Framework",
          "99.21%"
        ],
        [
          "Wang et al. (2026)",
          "98.56%"
        ],
        [
          "Chhibber et al. (2026)",
          "97.85%"
        ]
      ],
      "table_note": null
    },
    {
      "table_title": "Accuracy comparison between our framework and state-of-the-art methods on the ISO-NE dataset.",
      "is_baseline": false,
      "group_ns": null,
      "headers": [
        "Method",
        "Accuracy"
      ],
      "data": [
        [
          "Our Framework",
          "98.95%"
        ],
        [
          "Wang et al. (2026)",
          "98.32%"
        ],
        [
          "Chhibber et al. (2026)",
          "97.51%"
        ]
      ],
      "table_note": null
    },
    {
      "table_title": "Causal relationships between variables in the AEMO dataset.",
      "is_baseline": false,
      "group_ns": null,
      "headers": [
        "Variable 1",
        "Variable 2",
        "Causal Relationship"
      ],
      "data": [
        [
          "Load",
          "Price",
          "Positive"
        ],
        [
          "Load",
          "Renewable",
          "Negative"
        ],
        [
          "Price",
          "Renewable",
          "Positive"
        ]
      ],
      "table_note": null
    },
    {
      "table_title": "Predicted values of the time series variables in the AEMO dataset.",
      "is_baseline": false,
      "group_ns": null,
      "headers": [
        "Time Step",
        "Load",
        "Price",
        "Renewable"
      ],
      "data": [
        [
          "1",
          "100",
          "50",
          "20"
        ],
        [
          "2",
          "120",
          "60",
          "30"
        ],
        [
          "3",
          "140",
          "70",
          "40"
        ]
      ],
      "table_note": null
    },
    {
      "table_title": "Causal relationships between variables in the ISO-NE dataset.",
      "is_baseline": false,
      "group_ns": null,
      "headers": [
        "Variable 1",
        "Variable 2",
        "Causal Relationship"
      ],
      "data": [
        [
          "Load",
          "Price",
          "Positive"
        ],
        [
          "Load",
          "Renewable",
          "Negative"
        ],
        [
          "Price",
          "Renewable",
          "Positive"
        ]
      ],
      "table_note": null
    },
    {
      "table_title": "Predicted values of the time series variables in the ISO-NE dataset.",
      "is_baseline": false,
      "group_ns": null,
      "headers": [
        "Time Step",
        "Load",
        "Price",
        "Renewable"
      ],
      "data": [
        [
          "1",
          "150",
          "70",
          "25"
        ],
        [
          "2",
          "180",
          "80",
          "35"
        ],
        [
          "3",
          "210",
          "90",
          "45"
        ]
      ],
      "table_note": null
    }
  ]
}