{
  "tables": [
    {
      "table_title": "User Satisfaction Scores for Different ReCAPTCHA Configurations",
      "is_baseline": false,
      "group_ns": null,
      "headers": [
        "Configuration",
        "Web",
        "Mobile",
        "Desktop"
      ],
      "data": [
        [
          "Type 1",
          "85",
          "80",
          "90"
        ],
        [
          "Type 2",
          "80",
          "85",
          "88"
        ],
        [
          "Type 3",
          "75",
          "90",
          "85"
        ]
      ],
      "table_note": null
    },
    {
      "table_title": "Bot Detection Rates for Different ReCAPTCHA Configurations",
      "is_baseline": false,
      "group_ns": null,
      "headers": [
        "Configuration",
        "Web",
        "Mobile",
        "Desktop"
      ],
      "data": [
        [
          "Type 1",
          "92",
          "90",
          "95"
        ],
        [
          "Type 2",
          "88",
          "93",
          "94"
        ],
        [
          "Type 3",
          "90",
          "95",
          "92"
        ]
      ],
      "table_note": null
    }
  ]
}