{
  "tables": [
    {
      "table_title": "Results on GLUE, SuperGLUE, and MultiNLI benchmarks.",
      "is_baseline": false,
      "group_ns": null,
      "headers": [
        "Benchmark",
        "Accuracy",
        "Robustness",
        "Efficiency"
      ],
      "data": [
        [
          "GLUE",
          "85.2%",
          "92.1%",
          "98.5%"
        ],
        [
          "SuperGLUE",
          "82.5%",
          "90.2%",
          "97.3%"
        ],
        [
          "MultiNLI",
          "80.1%",
          "88.5%",
          "96.2%"
        ]
      ],
      "table_note": null
    }
  ]
}