{
  "tables": [
    {
      "table_title": "Performance of Different Deep Learning Architectures Under Varying Conditions",
      "is_baseline": false,
      "group_ns": null,
      "headers": [
        "Model",
        "Accuracy",
        "Precision",
        "Recall",
        "F1 Score"
      ],
      "data": [
        [
          "VGG16",
          "78.5%",
          "79.2%",
          "77.8%",
          "78.3%"
        ],
        [
          "ResNet",
          "85.6%",
          "86.2%",
          "85.0%",
          "85.6%"
        ],
        [
          "DenseNet",
          "81.2%",
          "82.1%",
          "80.3%",
          "81.2%"
        ]
      ],
      "table_note": "Performance metrics of various deep learning models evaluated under different conditions."
    }
  ]
}