{
  "tables": [
    {
      "table_title": "Performance Metrics for Different Datasets",
      "is_baseline": false,
      "group_ns": null,
      "headers": [
        "Dataset",
        "Accuracy",
        "Fairness Score",
        "Explainability Score"
      ],
      "data": [
        [
          "Adult Income",
          "87.5%",
          "0.85",
          "0.92"
        ],
        [
          "Credit Risk",
          "92.1%",
          "0.88",
          "0.90"
        ],
        [
          "Healthcare",
          "94.3%",
          "0.90",
          "0.93"
        ]
      ],
      "table_note": "The results indicate that our framework significantly improves fairness and explainability without compromising model accuracy."
    }
  ]
}